lsframe/__init__.py
lsframe/engine.py
lsframe/intake.py
lsframe/start.py
lsframe/version.py
lsframe/tools/__init__.py
lsframe/tools/sea_born.py
lsframe/tools/utest.py
lsframe/tools/utest2.py
unittests/__init__.py
unittests/test_lsframe.py
lsframe-1.0.dist-info/LICENSE.txt
lsframe-1.0.dist-info/METADATA
lsframe-1.0.dist-info/WHEEL
lsframe-1.0.dist-info/entry_points.txt
lsframe-1.0.dist-info/top_level.txt
lsframe-1.0.dist-info/RECORD
