Metadata-Version: 2.1
Name: lsframe
Version: 1.0
Summary: lsframe - map, classify, frame
Home-page: https://github.com/thcasey3/lsframe
Author: Thomas Casey
License: MIT
Download-URL: https://github.com/thcasey3/lsframe/
Project-URL: Homepage, https://thcasey3.github.io/lsframe/
Project-URL: Documentation, https://thcasey3.github.io/lsframe/
Project-URL: Source, https://github.com/thcasey3/lsframe/
Keywords: classify language recognition
Platform: UNKNOWN
Classifier: Development Status :: 3 - Alpha
Classifier: License :: OSI Approved :: MIT License
Classifier: Programming Language :: Python :: 3
Requires-Python: >=3.6
Requires-Dist: python-dateutil (>=2.6.1)
Requires-Dist: numpy (>=1.13.3)
Requires-Dist: pandas (>=1.0.4)
Requires-Dist: seaborn (>=0.10)
